lib_ml_group3/__init__.py
lib_ml_group3/load_model.py
lib_ml_group3/preprocessing.py
lib_ml_group3-0.3.11.dist-info/LICENSE
lib_ml_group3-0.3.11.dist-info/METADATA
lib_ml_group3-0.3.11.dist-info/WHEEL
lib_ml_group3-0.3.11.dist-info/RECORD
