Metadata-Version: 2.1
Name: lib-ml-group3
Version: 0.3.11
Summary: A library for pre-processing data used in machine learning models
Home-page: https://github.com/remla24-team3/lib-ml
License: MIT
Author: Jasper Bruin
Author-email: j.jasperbruin@tudelft.nl
Requires-Python: >=3.9,<3.13
Classifier: License :: OSI Approved :: MIT License
Classifier: Programming Language :: Python :: 3
Classifier: Programming Language :: Python :: 3.9
Classifier: Programming Language :: Python :: 3.10
Classifier: Programming Language :: Python :: 3.11
Classifier: Programming Language :: Python :: 3.12
Requires-Dist: keras (>=3.3.3,<4.0.0)
Requires-Dist: numpy (>=1.23.4,<2.0.0)
Requires-Dist: pylint (==3.1.0)
Requires-Dist: scikit-learn (>=1.4.2,<2.0.0)
Requires-Dist: tensorflow (>=2.16.1,<3.0.0)
Project-URL: Repository, https://github.com/remla24-team3/lib-ml
